setup.py
img4it.egg-info/PKG-INFO
img4it.egg-info/SOURCES.txt
img4it.egg-info/dependency_links.txt
img4it.egg-info/entry_points.txt
img4it.egg-info/namespace_packages.txt
img4it.egg-info/requires.txt
img4it.egg-info/top_level.txt
orangecontrib/__init__.py
orangecontrib/IMG4IT/__init__.py
orangecontrib/IMG4IT/utils/__init__.py
orangecontrib/IMG4IT/utils/compute_embedding_16b.py
orangecontrib/IMG4IT/utils/image_overlay_viewer.py
orangecontrib/IMG4IT/utils/reacalage_image.py
orangecontrib/IMG4IT/utils/tiff16_viewer.py
orangecontrib/IMG4IT/widgets/OW16bit_image_viewer.py
orangecontrib/IMG4IT/widgets/OWConvertImages.py
orangecontrib/IMG4IT/widgets/OWCreateEmbeddingsImage16bit.py
orangecontrib/IMG4IT/widgets/OWImageApplyTransform.py
orangecontrib/IMG4IT/widgets/OWPaddleOCR.py
orangecontrib/IMG4IT/widgets/OWRigidTransform.py
orangecontrib/IMG4IT/widgets/__init__.py
orangecontrib/IMG4IT/widgets/dinoV2Model.py
orangecontrib/IMG4IT/widgets/resnet50Model.py
orangecontrib/IMG4IT/widgets/designer/__init__.py
orangecontrib/IMG4IT/widgets/designer/owembedding_img16b.ui
orangecontrib/IMG4IT/widgets/designer/owmodel_dinoV2.ui
orangecontrib/IMG4IT/widgets/designer/owmodel_resnet50.ui
orangecontrib/IMG4IT/widgets/designer/owpaddleocr.ui
orangecontrib/IMG4IT/widgets/icons/__init__.py
orangecontrib/IMG4IT/widgets/icons/dinoV2.png
orangecontrib/IMG4IT/widgets/icons/embedding_Xray.png
orangecontrib/IMG4IT/widgets/icons/image_transform.png
orangecontrib/IMG4IT/widgets/icons/img4it.svg
orangecontrib/IMG4IT/widgets/icons/paddleocr.svg
orangecontrib/IMG4IT/widgets/icons/recalage.png
orangecontrib/IMG4IT/widgets/icons/resize-picture.svg
orangecontrib/IMG4IT/widgets/icons/resnet50.png
orangecontrib/IMG4IT/widgets/icons/viewer_xray_icon.png
orangecontrib/IMG4IT/widgets/icons_dev/__init__.py