Metadata-Version: 2.1
Name: img4it
Version: 1.0.6.991
Summary: Exploit computer vision technology with Orange Data Mining !
Home-page: 
Author: Orange community
Author-email: 
Keywords: orange3 add-on
